perception_pipeline/__init__.py
perception_pipeline/_version.py
perception_pipeline/backbone_agent/__init__.py
perception_pipeline/backbone_agent/backbone_agent.py
perception_pipeline/geometric_attribute_detection_agent/__init__.py
perception_pipeline/geometric_attribute_detection_agent/geometric_attribute_detection_agent.py
perception_pipeline/object_classification_agent/__init__.py
perception_pipeline/object_classification_agent/object_classification_agent.py
perception_pipeline/object_detection_agent/__init__.py
perception_pipeline/object_detection_agent/object_detection_agent.py
perception_pipeline/part_detection_agent/__init__.py
perception_pipeline/part_detection_agent/part_detection_agent.py
perception_pipeline/photometric_attribute_detection_agent/__init__.py
perception_pipeline/photometric_attribute_detection_agent/photometric_attribute_detection_agent.py
perception_pipeline/saliency_map_agent/__init__.py
perception_pipeline/saliency_map_agent/saliency_map_agent.py
perception_pipeline/uncertainty_attribution_agent/__init__.py
perception_pipeline/uncertainty_attribution_agent/uncertainty_attribution_agent.py
whyis_activitystreams/__init__.py
whyis_activitystreams/_version.py
whyis_activitystreams/plugin.py
whyis_activitystreams/activity_agent/__init__.py
whyis_activitystreams/activity_agent/activity_agent.py
whyis_activitystreams-0.1.4.dist-info/LICENSE
whyis_activitystreams-0.1.4.dist-info/METADATA
whyis_activitystreams-0.1.4.dist-info/WHEEL
whyis_activitystreams-0.1.4.dist-info/entry_points.txt
whyis_activitystreams-0.1.4.dist-info/top_level.txt
whyis_activitystreams-0.1.4.dist-info/RECORD
