Metadata-Version: 2.1
Name: whyis-activitystreams
Version: 0.1.4
Summary: A whyis plugin to support the interpretation of activity streams.
License-File: LICENSE
Requires-Dist: whyis
